{
  "api/Platform.Numbers.Arithmetic.html": {
    "href": "api/Platform.Numbers.Arithmetic.html",
    "title": "Class Arithmetic | LinksPlatform's Platform.Numbers Library",
    "keywords": "Class Arithmetic Represents a set of arithmetic methods. Представляет набор арифметических методов. Inheritance Object Arithmetic Inherited Members Object.Equals(Object) Object.Equals(Object, Object) Object.GetHashCode() Object.GetType() Object.MemberwiseClone() Object.ReferenceEquals(Object, Object) Object.ToString() Namespace : Platform.Numbers Assembly : Platform.Numbers.dll Syntax public static class Arithmetic Methods | Improve this Doc View Source Add<T>(T, T) Performing adding the x and y arguments. Выполняет сложение аргументов х и у. Declaration public static T Add<T>(T x, T y) Parameters Type Name Description T x The first term. Первое слагаемое. T y The second term. Второе слагаемое. Returns Type Description T Sum of x and y. Сумма x и y. Type Parameters Name Description T The numbers' type. Тип чисел. | Improve this Doc View Source Decrement<T>(T) Decreases number by one. Уменьшение числа на единицу. Declaration public static T Decrement<T>(T x) Parameters Type Name Description T x The number to reduce. Число для уменьшения. Returns Type Description T Decreased by one number. Уменьшенное на единицу число. Type Parameters Name Description T The number's type. Тип числа. | Improve this Doc View Source Decrement<T>(ref T) Decreases the value of the argument by one. Уменьшает значение аргумента на единицу. Declaration public static T Decrement<T>(ref T x) Parameters Type Name Description T x The argument to reduce. Аргумент для уменьшения. Returns Type Description T Decreased argument value. Уменьшеное значение аргумента. Type Parameters Name Description T The number's type. Тип числа. | Improve this Doc View Source Divide<T>(T, T) Performs dividing x by y. Выполняет деление х на у. Declaration public static T Divide<T>(T x, T y) Parameters Type Name Description T x Dividend. Делимое. T y Divider. Делитель. Returns Type Description T Quoitent of x and y. Частное x и y. Type Parameters Name Description T The numbers' type. Тип чисел. | Improve this Doc View Source Increment<T>(T) Increasing the number by one. Увеличивает число на единицу. Declaration public static T Increment<T>(T x) Parameters Type Name Description T x The number to increase. Число для увеличения. Returns Type Description T Increase by one number. Увеличенное на единицу число. Type Parameters Name Description T The number's type. Тип числа. | Improve this Doc View Source Increment<T>(ref T) Increases the value of argument by one. Увеличивает значение аргумента на единицу. Declaration public static T Increment<T>(ref T x) Parameters Type Name Description T x The argument to increase. Аргумент для увеличения. Returns Type Description T Increased argument value. Увеличенное значение аргумента. Type Parameters Name Description T The number's type. Тип числа. | Improve this Doc View Source Multiply<T>(T, T) Performs multiplication x by y. Выполняет умножение х на у. Declaration public static T Multiply<T>(T x, T y) Parameters Type Name Description T x First multiplier. Первый множитель. T y Second multiplier. Второй множитель. Returns Type Description T Product of x and y. Произведение x и y. Type Parameters Name Description T The numbers' type. Тип чисел. | Improve this Doc View Source Subtract<T>(T, T) Performs subtracting y from x. Выполняет вычитание y из x. Declaration public static T Subtract<T>(T x, T y) Parameters Type Name Description T x Minuend. Уменьшаемое. T y Subtrahend. Вычитаемое. Returns Type Description T Difference between x and y. Разность между x и y. Type Parameters Name Description T The numbers' type. Тип чисел."
  },
  "api/Platform.Numbers.Arithmetic-1.html": {
    "href": "api/Platform.Numbers.Arithmetic-1.html",
    "title": "Class Arithmetic<T> | LinksPlatform's Platform.Numbers Library",
    "keywords": "Class Arithmetic<T> Represents a set of compiled arithmetic operations delegates. Представляет набор скомпилированных делегатов арифметических операций. Inheritance Object Arithmetic<T> Inherited Members Object.Equals(Object) Object.Equals(Object, Object) Object.GetHashCode() Object.GetType() Object.MemberwiseClone() Object.ReferenceEquals(Object, Object) Object.ToString() Namespace : Platform.Numbers Assembly : Platform.Numbers.dll Syntax public static class Arithmetic<T> Type Parameters Name Description T Fields | Improve this Doc View Source Add A read-only field that represents a addition function delegate. Поле только для чтения, представляющее делегат функции сложения. Declaration public static readonly Func<T, T, T> Add Field Value Type Description Func <T, T, T> | Improve this Doc View Source Decrement A read-only field that represents a decrement function delegate. Поле только для чтения, представляющее делегат функции декремента. Declaration public static readonly Func<T, T> Decrement Field Value Type Description Func <T, T> | Improve this Doc View Source Divide A read-only field that represents a division function delegate. Поле только для чтения, представляющее делегат функции деления. Declaration public static readonly Func<T, T, T> Divide Field Value Type Description Func <T, T, T> | Improve this Doc View Source Increment A read-only field that represents a increment function delegate. Поле только для чтения, представляющее делегат функции инкремента. Declaration public static readonly Func<T, T> Increment Field Value Type Description Func <T, T> | Improve this Doc View Source Multiply A read-only field that represents a multiplication function delegate. Поле только для чтения, представляющее делегат функции умножения. Declaration public static readonly Func<T, T, T> Multiply Field Value Type Description Func <T, T, T> | Improve this Doc View Source Subtract A read-only field that represents a subtraction function delegate. Поле только для чтения, представляющее делегат функции вычитания. Declaration public static readonly Func<T, T, T> Subtract Field Value Type Description Func <T, T, T>"
  },
  "api/Platform.Numbers.ArithmeticExtensions.html": {
    "href": "api/Platform.Numbers.ArithmeticExtensions.html",
    "title": "Class ArithmeticExtensions | LinksPlatform's Platform.Numbers Library",
    "keywords": "Class ArithmeticExtensions Represents a set of extension methods that perform arithmetic operations on arbitrary object types. Представляет набор методов расширения выполняющих арифметические операции для объектов произвольного типа. Inheritance Object ArithmeticExtensions Inherited Members Object.Equals(Object) Object.Equals(Object, Object) Object.GetHashCode() Object.GetType() Object.MemberwiseClone() Object.ReferenceEquals(Object, Object) Object.ToString() Namespace : Platform.Numbers Assembly : Platform.Numbers.dll Syntax public static class ArithmeticExtensions Methods | Improve this Doc View Source Decrement<T>(ref T) Decrements the variable passed as an argument by one. Уменьшает переданную в качестве аргумента переменную на единицу. Declaration public static T Decrement<T>(this ref T x) where T : struct Parameters Type Name Description T x The reference to the decremented variable. Ссылка на уменьшаемую переменную. Returns Type Description T The value of the argument decremented by one. Уменьшеное значение аргумента на единицу. Type Parameters Name Description T The number's type. Тип числа. | Improve this Doc View Source Increment<T>(ref T) Increments the variable passed as an argument by one. Увеличивает переданную в качестве аргумента переменную на единицу. Declaration public static T Increment<T>(this ref T x) where T : struct Parameters Type Name Description T x The reference to the incremented variable. Ссылка на увеличиваемую переменную. Returns Type Description T The value of the argument incremented by one. Увеличенное значение аргумента на единицу. Type Parameters Name Description T The number's type. Тип числа."
  },
  "api/Platform.Numbers.Bit.html": {
    "href": "api/Platform.Numbers.Bit.html",
    "title": "Class Bit | LinksPlatform's Platform.Numbers Library",
    "keywords": "Class Bit A set of operations on the set bits of a number. Набор операций над установленными битами числа. Inheritance Object Bit Inherited Members Object.Equals(Object) Object.Equals(Object, Object) Object.GetHashCode() Object.GetType() Object.MemberwiseClone() Object.ReferenceEquals(Object, Object) Object.ToString() Namespace : Platform.Numbers Assembly : Platform.Numbers.dll Syntax public static class Bit Methods | Improve this Doc View Source And<T>(T, T) Performs bitwise numbers multiplication. Выполняет побитовое умножение чисел. The numbers' type. Тип чисел. Declaration public static T And<T>(T x, T y) Parameters Type Name Description T x First multiplier. Первый множитель. T y Second multiplier. Второй множитель. Returns Type Description T Logical product of numbers. Логическое произведение чисел. Type Parameters Name Description T | Improve this Doc View Source Count(Int64) Counts the number of bits set in a number. Подсчитывает количество установленных бит в числе. Declaration public static long Count(long x) Parameters Type Name Description Int64 x Bitwise number. Число в битовом представлении. Returns Type Description Int64 Number of bits set in a number. Количество установленных бит в числе. | Improve this Doc View Source GetLowestPosition(UInt64) Searches for the first bit set in a number. Ищет первый установленный бит в числе. Declaration public static int GetLowestPosition(ulong value) Parameters Type Name Description UInt64 value Bitwise number. Число в битовом представлении. Returns Type Description Int32 First bit set. Первый установленный бит. | Improve this Doc View Source Not<T>(T) Performing bitwise inversion of a number. Выполняет побитовую инверсию числа. Declaration public static T Not<T>(T x) Parameters Type Name Description T x Number to invert. Число для инверсии. Returns Type Description T Inverse value of the number. Обратное значение числа. Type Parameters Name Description T The number's type. Тип числа. | Improve this Doc View Source Or<T>(T, T) Performing bitwise numbers addition. Выполняет побитовое сложение чисел. Declaration public static T Or<T>(T x, T y) Parameters Type Name Description T x First term. Первое слагаемое. T y Second term. Второе слагаемое. Returns Type Description T The logical sum of numbers Логическая сумма чисел. Type Parameters Name Description T The numbers' type. Тип чисел. | Improve this Doc View Source PartialRead<T>(T, Int32, Int32) Reads a specified number of bits from the number at specified position. Считывает указанное количество бит из числа в указанной позиции. Declaration public static T PartialRead<T>(T target, int shift, int limit) Parameters Type Name Description T target The number from which the partial read will be performed. Число из которого будет выполнено частичное чтение. Int32 shift The start position to read from. Стартовая позиция чтения. Int32 limit The number of bits to read. Количество бит, которые нужно считать. Returns Type Description T The number consisting of bits read from the source number. Число состоящее из считанных из исходного числа бит. Type Parameters Name Description T The number's type. Тип числа. | Improve this Doc View Source PartialWrite<T>(T, T, Int32, Int32) Performs a partial write of a specified number of bits from source number to target number. Выполняет частичную запись определенного количества бит исходного числа в целевое число. Declaration public static T PartialWrite<T>(T target, T source, int shift, int limit) Parameters Type Name Description T target The value to which the partial write will be performed. Значение в которое будет выполнена частичная запись. T source Data source for recording. Источник данных для записи. Int32 shift The start position to read from. Стартовая позиция чтения. Int32 limit The number of bits to write from source to target. Количество бит, которые нужно записать из source в target. Returns Type Description T The target number updated with bits from source number. Целевое число с обновленными битами из исходного числа. Type Parameters Name Description T The numbers' type. Тип чисел. | Improve this Doc View Source ShiftLeft<T>(T, Int32) Performs a bitwise shift of a number to the left by the specified number of bits. Выполняет побитовый свиг числа влево на указанное количество бит. Declaration public static T ShiftLeft<T>(T x, int y) Parameters Type Name Description T x The number on which the left bitwise shift operation will be performed. Число над которым будет производиться операция пиботового смещения влево. Int32 y The number of bits to shift. Количество бит на которые выполнить смещение. Returns Type Description T The value with discarded high-order bits that are outside the range of the number's type and set low-order empty bit positions to zero. Значение с отброшенными старшими битами, которые находятся за пределами диапазона типа числа и устанавливленными пустыми битовыми позициями младших разрядов в ноль. Type Parameters Name Description T The number's type. Тип числа. | Improve this Doc View Source ShiftRight<T>(T, Int32) Performs a bitwise shift of a number to the right by the specified number of bits. Выполняет побитовый свиг числа вправо на указанное количество бит. Declaration public static T ShiftRight<T>(T x, int y) Parameters Type Name Description T x The number on which the right bitwise shift operation will be performed. Число над которым будет производиться операция побитового смещения вправо. Int32 y The number of bits to shift. Количество бит на которые выполнить смещение. Returns Type Description T The value with discarded low-order bits. Значение с отброшенными младшими битами. Type Parameters Name Description T The number's type. Тип числа."
  },
  "api/Platform.Numbers.Bit-1.html": {
    "href": "api/Platform.Numbers.Bit-1.html",
    "title": "Class Bit<T> | LinksPlatform's Platform.Numbers Library",
    "keywords": "Class Bit<T> Represents a set of compiled bit operations delegates. Представляет набор скомпилированных делегатов битовых операций. Inheritance Object Bit<T> Inherited Members Object.Equals(Object) Object.Equals(Object, Object) Object.GetHashCode() Object.GetType() Object.MemberwiseClone() Object.ReferenceEquals(Object, Object) Object.ToString() Namespace : Platform.Numbers Assembly : Platform.Numbers.dll Syntax public static class Bit<T> Type Parameters Name Description T Fields | Improve this Doc View Source And A read-only field that represents a logic multiplication function delegate. Поле только для чтения, представляющее делегат функции логического умножения. Declaration public static readonly Func<T, T, T> And Field Value Type Description Func <T, T, T> | Improve this Doc View Source Not A read-only field that represents a bitwise inversion function delegate. Поле только для чтения, представляющее делегат функции побитовой инверсии числа. Declaration public static readonly Func<T, T> Not Field Value Type Description Func <T, T> | Improve this Doc View Source Or A read-only field that represents a logic addition function delegate. Поле только для чтения, представляющее делегат функции логического сложения. Declaration public static readonly Func<T, T, T> Or Field Value Type Description Func <T, T, T> | Improve this Doc View Source PartialRead A read-only field that represents a bitwise number representation partial read function delegate. Поле только для чтения, представляющее делегат функции частичного побитового считывания числа. Declaration public static readonly Func<T, int, int, T> PartialRead Field Value Type Description Func <T, Int32 , Int32 , T> | Improve this Doc View Source PartialWrite A read-only field that represents a bitwise number representation partial rewrite function delegate. Поле только для чтения, представляющее делегат функции частичной побитовой перезаписи представления числа. Declaration public static readonly Func<T, T, int, int, T> PartialWrite Field Value Type Description Func <T, T, Int32 , Int32 , T> | Improve this Doc View Source ShiftLeft A read-only field that represents a bitwise left shift function delegate. Поле только для чтения, представляющее делегат функции побитового сдвига числа влево. Declaration public static readonly Func<T, int, T> ShiftLeft Field Value Type Description Func <T, Int32 , T> | Improve this Doc View Source ShiftRight A read-only field that represents a bitwise right shift function delegate. Поле только для чтения, представляющее делегат функции побитового сдвига числа вправо. Declaration public static readonly Func<T, int, T> ShiftRight Field Value Type Description Func <T, Int32 , T>"
  },
  "api/Platform.Numbers.BitwiseExtensions.html": {
    "href": "api/Platform.Numbers.BitwiseExtensions.html",
    "title": "Class BitwiseExtensions | LinksPlatform's Platform.Numbers Library",
    "keywords": "Class BitwiseExtensions Represents a set of bitwise operation. Представляет набор битовых операций. Inheritance Object BitwiseExtensions Inherited Members Object.Equals(Object) Object.Equals(Object, Object) Object.GetHashCode() Object.GetType() Object.MemberwiseClone() Object.ReferenceEquals(Object, Object) Object.ToString() Namespace : Platform.Numbers Assembly : Platform.Numbers.dll Syntax public static class BitwiseExtensions Methods | Improve this Doc View Source Not<T>(ref T) Performs bitwise inversion of a number. Выполняет побитовую инверсию числа. Declaration public static T Not<T>(this ref T target) where T : struct Parameters Type Name Description T target The number to invert. Число для инверсии. Returns Type Description T An inverted value of the number. Обратное значение числа. Type Parameters Name Description T The number's type. Тип числа. | Improve this Doc View Source PartialRead<T>(T, Int32, Int32) Reads a specified number of bits from the number at specified position. Считывает указанное количество бит из числа в указанной позиции. Declaration public static T PartialRead<T>(this T target, int shift, int limit) Parameters Type Name Description T target The number from which the partial read will be performed. Число из которого будет выполнено частичное чтение. Int32 shift The start position to read from. Стартовая позиция чтения. Int32 limit The number of bits to read. Количество бит, которые нужно считать. Returns Type Description T The number consisting of bits read from the source number. Число состоящее из считанных из исходного числа бит. Type Parameters Name Description T The number's type. Тип числа. | Improve this Doc View Source PartialWrite<T>(ref T, T, Int32, Int32) Performs a partial write of a specified number of bits from source number to target number. Выполняет частичную запись определенного количества бит исходного числа в целевое число. Declaration public static T PartialWrite<T>(this ref T target, T source, int shift, int limit) where T : struct Parameters Type Name Description T target The value to which the partial write will be performed. Значение в которое будет выполнена частичная запись. T source Data source for writing. Источник данных для записи. Int32 shift The start position to read from. Стартовая позиция чтения. Int32 limit The number of bits to write from source to target. Количество бит, которые нужно записать из source в target. Returns Type Description T The target number updated with bits from source number. Целевое число с обновленными битами из исходного числа. Type Parameters Name Description T The numbers' type. Тип чисел."
  },
  "api/Platform.Numbers.html": {
    "href": "api/Platform.Numbers.html",
    "title": "Namespace Platform.Numbers | LinksPlatform's Platform.Numbers Library",
    "keywords": "Namespace Platform.Numbers Classes Arithmetic Represents a set of arithmetic methods. Представляет набор арифметических методов. Arithmetic<T> Represents a set of compiled arithmetic operations delegates. Представляет набор скомпилированных делегатов арифметических операций. ArithmeticExtensions Represents a set of extension methods that perform arithmetic operations on arbitrary object types. Представляет набор методов расширения выполняющих арифметические операции для объектов произвольного типа. Bit A set of operations on the set bits of a number. Набор операций над установленными битами числа. Bit<T> Represents a set of compiled bit operations delegates. Представляет набор скомпилированных делегатов битовых операций. BitwiseExtensions Represents a set of bitwise operation. Представляет набор битовых операций. Math Represents a set of math methods. Представляет набор математических методов. Math<T> Represents a set of compiled math operations delegates. Представляет набор скомпилированных делегатов математических операций. MathExtensions Represents a set of extension methods that perform mathematical operations on arbitrary object types. Представляет набор методов расширения выполняющих математические операции для объектов произвольного типа."
  },
  "api/Platform.Numbers.Math.html": {
    "href": "api/Platform.Numbers.Math.html",
    "title": "Class Math | LinksPlatform's Platform.Numbers Library",
    "keywords": "Class Math Represents a set of math methods. Представляет набор математических методов. Inheritance Object Math Inherited Members Object.Equals(Object) Object.Equals(Object, Object) Object.GetHashCode() Object.GetType() Object.MemberwiseClone() Object.ReferenceEquals(Object, Object) Object.ToString() Namespace : Platform.Numbers Assembly : Platform.Numbers.dll Syntax public static class Math Remarks Resizable array (FileMappedMemory) for values cache may be used. or cached oeis.org Fields | Improve this Doc View Source MaximumCatalanIndex Represents the limit for calculating the factorial number, supported by the UInt64 type. Представляет предел расчёта факториала числа, поддерживаемый UInt64 типом. Declaration public static readonly ulong MaximumCatalanIndex Field Value Type Description UInt64 | Improve this Doc View Source MaximumFactorialNumber Represents the limit for calculating the catanal number, supported by the UInt64 type. Представляет предел расчёта катаналового числа, поддерживаемый UInt64 типом. Declaration public static readonly ulong MaximumFactorialNumber Field Value Type Description UInt64 Methods | Improve this Doc View Source Abs<T>(T) Takes a module from a number. Берёт модуль от числа. Declaration public static T Abs<T>(T x) Parameters Type Name Description T x The number from which to take the absolute value. Число, от которого необходимо взять абсолютное значение. Returns Type Description T The absolute value of the number. Абсолютное значение числа. Type Parameters Name Description T The number's type. Тип числа. | Improve this Doc View Source Catalan(UInt64) Returns the Catalan Number with the number specified as an argument. Возвращает Число Катанала с номером, указанным в качестве аргумента. Declaration public static ulong Catalan(ulong n) Parameters Type Name Description UInt64 n The number of the Catalan number. Номер Числа Катанала. Returns Type Description UInt64 The Catalan Number with the number specified as an argument. Число Катанала с номером, указанным в качестве аргумента. | Improve this Doc View Source Factorial(UInt64) Returns the product of all positive integers less than or equal to the number specified as an argument. Возвращает произведение всех положительных чисел меньше или равных указанному в качестве аргумента числу. Declaration public static ulong Factorial(ulong n) Parameters Type Name Description UInt64 n The maximum positive number that will participate in factorial's product. Максимальное положительное число, которое будет участвовать в произведении факториала. Returns Type Description UInt64 The product of all positive integers less than or equal to the number specified as an argument. Произведение всех положительных чисел меньше или равных указанному, в качестве аргумента, числу. | Improve this Doc View Source IsPowerOfTwo(UInt64) Checks if a number is a power of two. Проверяет, является ли число степенью двойки. Declaration public static bool IsPowerOfTwo(ulong x) Parameters Type Name Description UInt64 x The number to check. Число для проверки. Returns Type Description Boolean True if the number is a power of two otherwise false. True, если число является степенью двойки, иначе - false. | Improve this Doc View Source Negate<T>(T) Makes a number negative. Делает число отрицательным. Declaration public static T Negate<T>(T x) Parameters Type Name Description T x The number to be made negative. Число которое нужно сделать отрицательным. Returns Type Description T A negative number. Отрицательное число. Type Parameters Name Description T The number's type. Тип числа."
  },
  "api/Platform.Numbers.Math-1.html": {
    "href": "api/Platform.Numbers.Math-1.html",
    "title": "Class Math<T> | LinksPlatform's Platform.Numbers Library",
    "keywords": "Class Math<T> Represents a set of compiled math operations delegates. Представляет набор скомпилированных делегатов математических операций. Inheritance Object Math<T> Inherited Members Object.Equals(Object) Object.Equals(Object, Object) Object.GetHashCode() Object.GetType() Object.MemberwiseClone() Object.ReferenceEquals(Object, Object) Object.ToString() Namespace : Platform.Numbers Assembly : Platform.Numbers.dll Syntax public static class Math<T> Type Parameters Name Description T Fields | Improve this Doc View Source Abs A read-only field that represents a number modulus calculation function delegate. Поле только для чтения, которое представляет делегат функции вычисления модуля числа. Declaration public static readonly Func<T, T> Abs Field Value Type Description Func <T, T> | Improve this Doc View Source Negate A read-only field that represents a number negation function delegate. Поле только для чтения, которое представляет делегат функции отрицания числа. Declaration public static readonly Func<T, T> Negate Field Value Type Description Func <T, T>"
  },
  "api/Platform.Numbers.MathExtensions.html": {
    "href": "api/Platform.Numbers.MathExtensions.html",
    "title": "Class MathExtensions | LinksPlatform's Platform.Numbers Library",
    "keywords": "Class MathExtensions Represents a set of extension methods that perform mathematical operations on arbitrary object types. Представляет набор методов расширения выполняющих математические операции для объектов произвольного типа. Inheritance Object MathExtensions Inherited Members Object.Equals(Object) Object.Equals(Object, Object) Object.GetHashCode() Object.GetType() Object.MemberwiseClone() Object.ReferenceEquals(Object, Object) Object.ToString() Namespace : Platform.Numbers Assembly : Platform.Numbers.dll Syntax public static class MathExtensions Methods | Improve this Doc View Source Abs<T>(ref T) Takes a module from a number. Берёт модуль от числа. Declaration public static T Abs<T>(this ref T x) where T : struct Parameters Type Name Description T x The number from which to take the absolute value. Число от которого необходимо взять абсолютное значение. Returns Type Description T The absolute value of a number. Абсолютное значение числа. Type Parameters Name Description T The number's type. Тип числа. | Improve this Doc View Source Negate<T>(ref T) Makes a number negative. Делает число отрицательным. Declaration public static T Negate<T>(this ref T x) where T : struct Parameters Type Name Description T x The number to be made negative. Число которое нужно сделать отрицательным. Returns Type Description T Negative number. Отрицательное число. Type Parameters Name Description T The number's type. Тип числа."
  },
  "README.html": {
    "href": "README.html",
    "title": "Numbers | LinksPlatform's Platform.Numbers Library",
    "keywords": "Numbers LinksPlatform's Platform.Numbers Class Library. Namespace: Platform.Numbers Forked from: Konard/LinksPlatform/Platform/Platform.Helpers/Numbers NuGet package: Platform.Numbers Documentation PDF file with code for e-readers. Depend on Platform.Converters Dependent libraries Platform.Unsafe Platform.Data"
  }
}